{
	"AWSTemplateFormatVersion": "2010-09-09",
	"Description": "AWS CloudFormation Template for deploying a Lambda function that calculates EC2 pricing in near real-time",
	"Parameters": {
  		"TagKey" : {
			"Type": "String",
    		"Description" : "Tag key that will be used to find AWS resources. Mandatory",
    		"MinLength": "1",
			"ConstraintDescription": "Tag key is mandatory."    		
  		}, 
  		"TagValue" : {
			"Type": "String",
    		"MinLength": "1",
    		"Description" : "Tag value that will be used to find AWS resources. Mandatory",
			"ConstraintDescription": "Tag value is mandatory."    		
  		}
  		
	},
	"Resources": {

           "LambdaRealtimeCalculatePricingRole": {
              "Type": "AWS::IAM::Role",
              "Properties": {
                "AssumeRolePolicyDocument": {
                  "Version": "2012-10-17",
                  "Statement": [{
                      "Effect": "Allow",
                      "Principal": {"Service": ["lambda.amazonaws.com"]},
                      "Action": ["sts:AssumeRole"]
                  }]
                },
                "Path": "/",
                "Policies": [{
                  "PolicyName": "root",
                  "PolicyDocument": {
                    "Version": "2012-10-17",
                    "Statement": [{
                        "Effect": "Allow",
                        "Action": ["logs:CreateLogGroup","logs:CreateLogStream","logs:PutLogEvents"],
                        "Resource": "arn:aws:logs:*:*:*"
                    },
                    {
                        "Effect": "Allow",
                        "Action": ["cloudwatch:*"],
                        "Resource": "*"
                    },
                    {
                        "Effect": "Allow",
                        "Action": ["ec2:Describe*",
                                   "elasticloadbalancing:Describe*",
                                   "autoscaling:Describe*"],
                        "Resource": "*"
                    },
                    {
                        "Effect": "Allow",
                        "Action": ["rds:Describe*",
                                   "rds:List*"],
                        "Resource": "*"
                    },
                    {
                        "Effect": "Allow",
                        "Action": ["dynamodb:Describe*",
                                   "dynamodb:List*"],
                        "Resource": "*"
                    },
                    {
                        "Effect": "Allow",
                        "Action": ["kinesis:Describe*",
                                   "kinesis:List*"],
                        "Resource": "*"
                    },
                    {
                        "Effect": "Allow",
                        "Action": ["lambda:GetFunctionConfiguration"],
                        "Resource": "*"
                    },
                    {
                        "Effect": "Allow",
                        "Action": ["tag:getResources", "tag:getTagKeys", "tag:getTagValues"],
                        "Resource": "*"
                    }

                    ]
                  }
                }]
              }
            },

		"LambdaRealtimeCalculatePricingFunction": {
		  "Type": "AWS::Lambda::Function",
          "DependsOn" : ["LambdaRealtimeCalculatePricingRole"],		  
		  "Properties": {
		    "Handler": "functions/calculate-near-realtime.handler",
		    "Role": { "Fn::GetAtt" : ["LambdaRealtimeCalculatePricingRole", "Arn"] },
		    "Code": {
		      "S3Bucket": { "Fn::Join" : [ "", ["concurrencylabs-deployment-artifacts-public-", { "Ref" : "AWS::Region" }] ] },
		      "S3Key": "lambda-near-realtime-pricing/calculate-near-realtime-pricing-v3.10.zip"
		    },
		    "Runtime": "python3.6",
		    "Timeout": "300",
		    "MemorySize" : 1024
		  }
		},


"ScheduledPricingCalculationRule": {
  "Type": "AWS::Events::Rule",
  "Properties": {
    "Description": "Invoke Pricing Calculator Lambda function every 5 minutes",
    "ScheduleExpression": "rate(5 minutes)",
    "State": "ENABLED",
    "Targets": [{
      "Arn": { "Fn::GetAtt": ["LambdaRealtimeCalculatePricingFunction", "Arn"] },
      "Id": "NearRealTimePriceCalculatorFunctionv1",
      "Input":{"Fn::Join":["", ["{\"tag\":{\"key\":\"",{"Ref":"TagKey"},"\",\"value\":\"",{"Ref":"TagValue"},"\"}}"]]}
    }]
  }
},


"PermissionForEventsToInvokePricingCalculationLambda": {
  "Type": "AWS::Lambda::Permission",
  "Properties": {
    "FunctionName": { "Ref": "LambdaRealtimeCalculatePricingFunction" },
    "Action": "lambda:InvokeFunction",
    "Principal": "events.amazonaws.com",
    "SourceArn": { "Fn::GetAtt": ["ScheduledPricingCalculationRule", "Arn"] }
  }
}

},

	"Outputs": {

		"Documentation": {
			"Description": "For more details, see this blog post",
			"Value": "https://www.concurrencylabs.com/blog/aws-pricing-lambda-realtime-calculation-function/"
		},


		"LambdaFunction": {
			"Description": "Lambda function that calculates pricing in near real-time",
			"Value": {
				"Ref": "LambdaRealtimeCalculatePricingFunction"
			}
		},

		"ScheduledEvent": {
			"Description": "CloudWatch Events schedule that will trigger the Lambda function",
			"Value": {
				"Ref": "ScheduledPricingCalculationRule"
			}
		}

	}
}
